crowdkit/__init__.py
crowdkit/py.typed
crowdkit/aggregation/__init__.py
crowdkit/aggregation/py.typed
crowdkit/aggregation/utils.py
crowdkit/aggregation/base/__init__.py
crowdkit/aggregation/base/py.typed
crowdkit/aggregation/classification/__init__.py
crowdkit/aggregation/classification/dawid_skene.py
crowdkit/aggregation/classification/glad.py
crowdkit/aggregation/classification/gold_majority_vote.py
crowdkit/aggregation/classification/kos.py
crowdkit/aggregation/classification/m_msr.py
crowdkit/aggregation/classification/mace.py
crowdkit/aggregation/classification/majority_vote.py
crowdkit/aggregation/classification/py.typed
crowdkit/aggregation/classification/wawa.py
crowdkit/aggregation/classification/zero_based_skill.py
crowdkit/aggregation/embeddings/__init__.py
crowdkit/aggregation/embeddings/closest_to_average.py
crowdkit/aggregation/embeddings/hrrasa.py
crowdkit/aggregation/embeddings/py.typed
crowdkit/aggregation/embeddings/rasa.py
crowdkit/aggregation/image_segmentation/__init__.py
crowdkit/aggregation/image_segmentation/py.typed
crowdkit/aggregation/image_segmentation/segmentation_em.py
crowdkit/aggregation/image_segmentation/segmentation_majority_vote.py
crowdkit/aggregation/image_segmentation/segmentation_rasa.py
crowdkit/aggregation/multilabel/__init__.py
crowdkit/aggregation/multilabel/binary_relevance.py
crowdkit/aggregation/pairwise/__init__.py
crowdkit/aggregation/pairwise/bradley_terry.py
crowdkit/aggregation/pairwise/noisy_bt.py
crowdkit/aggregation/pairwise/py.typed
crowdkit/aggregation/texts/__init__.py
crowdkit/aggregation/texts/py.typed
crowdkit/aggregation/texts/rover.py
crowdkit/aggregation/texts/text_hrrasa.py
crowdkit/aggregation/texts/text_rasa.py
crowdkit/datasets/__init__.py
crowdkit/datasets/_base.py
crowdkit/datasets/_loaders.py
crowdkit/datasets/load_dataset.py
crowdkit/datasets/py.typed
crowdkit/learning/__init__.py
crowdkit/learning/conal.py
crowdkit/learning/crowd_layer.py
crowdkit/learning/py.typed
crowd_kit-1.4.1.dist-info/AUTHORS
crowd_kit-1.4.1.dist-info/LICENSE
crowd_kit-1.4.1.dist-info/METADATA
crowd_kit-1.4.1.dist-info/WHEEL
crowd_kit-1.4.1.dist-info/top_level.txt
crowd_kit-1.4.1.dist-info/zip-safe
crowd_kit-1.4.1.dist-info/RECORD
