Metadata-Version: 2.1
Name: crowd-kit
Version: 1.4.1
Summary: Computational Quality Control for Crowdsourcing
Author: Toloka
License: Apache 2.0
Project-URL: Homepage, https://github.com/Toloka/crowd-kit
Project-URL: Bug Tracker, https://github.com/Toloka/crowd-kit/issues
Project-URL: Documentation, https://crowd-kit.readthedocs.io/
Project-URL: API Reference, https://crowd-kit.readthedocs.io/
Project-URL: Source Code, https://github.com/Toloka/crowd-kit
Project-URL: Release Notes, https://github.com/Toloka/crowd-kit/blob/main/CHANGELOG.md
Keywords: crowdsourcing,data labeling,answer aggregation,truth inference,learning from crowds,machine learning,quality control,data quality
Classifier: Development Status :: 5 - Production/Stable
Classifier: Intended Audience :: Developers
Classifier: Intended Audience :: Science/Research
Classifier: License :: OSI Approved :: Apache Software License
Classifier: Operating System :: OS Independent
Classifier: Programming Language :: Python
Classifier: Programming Language :: Python :: 3
Classifier: Programming Language :: Python :: 3.8
Classifier: Programming Language :: Python :: 3.9
Classifier: Programming Language :: Python :: 3.10
Classifier: Programming Language :: Python :: 3.11
Classifier: Programming Language :: Python :: 3.12
Classifier: Programming Language :: Python :: Implementation :: CPython
Classifier: Topic :: Scientific/Engineering
Classifier: Topic :: Software Development
Classifier: Typing :: Typed
Requires-Python: >=3.8
License-File: LICENSE
License-File: AUTHORS
Requires-Dist: attrs
Requires-Dist: nltk
Requires-Dist: numpy
Requires-Dist: pandas>=1.1.0
Requires-Dist: pyarrow
Requires-Dist: scikit-learn
Requires-Dist: tqdm
Requires-Dist: transformers
Provides-Extra: dev
Requires-Dist: black; extra == "dev"
Requires-Dist: build; extra == "dev"
Requires-Dist: codecov; extra == "dev"
Requires-Dist: flake8; extra == "dev"
Requires-Dist: ipywidgets; extra == "dev"
Requires-Dist: isort; extra == "dev"
Requires-Dist: mypy; extra == "dev"
Requires-Dist: nbqa; extra == "dev"
Requires-Dist: notebook; extra == "dev"
Requires-Dist: pandas-stubs; extra == "dev"
Requires-Dist: pre-commit; extra == "dev"
Requires-Dist: pytest; extra == "dev"
Requires-Dist: pyupgrade; extra == "dev"
Requires-Dist: twine; extra == "dev"
Requires-Dist: types-tqdm; extra == "dev"
Provides-Extra: docs
Requires-Dist: mkdocs-material; extra == "docs"
Requires-Dist: mkdocstrings-python; extra == "docs"
Provides-Extra: learning
Requires-Dist: torch>=1.6.0; extra == "learning"
Requires-Dist: transformers>=4.0.0; extra == "learning"
